{
    "ainu1240": {
        "glossing": {
            "words": {
                "accuracy": {
                    "macro": 0.877509239818562,
                    "micro": 0.8846153846153846
                },
                "bleu": 0.747856427681572,
                "error_rate": 0.12152223717901704
            },
            "morphemes": {
                "accuracy": {
                    "macro": 0.8232935995093665,
                    "micro": 0.8110941992220531
                },
                "classes": {
                    "stem": {
                        "prec": 0.7987557479037057,
                        "rec": 0.7855812716147912,
                        "f1": 0.7921137339055794
                    },
                    "gram": {
                        "prec": 0.8843799195382194,
                        "rec": 0.883298392732355,
                        "f1": 0.8838388252775107
                    }
                },
                "bleu": 0.8690464362385188,
                "error_rate": 0.1086770106887354
            },
            "characters": {
                "error_rate": 0.1055991835285181
            }
        },
        "segmentation": {
            "accuracy": 0.7491525423728813,
            "precision": 0.9513110755860666,
            "recall": 0.9521411549170123,
            "f1": 0.9509388774707167,
            "edit_distance": 0.4728813559322034
        },
        "alignment": 1.0
    },
    "arap1274": {
        "glossing": {
            "words": {
                "accuracy": {
                    "macro": 0.7525236751455123,
                    "micro": 0.7799894310375198
                },
                "bleu": 0.6117977625901344,
                "error_rate": 0.2470540087842481
            },
            "morphemes": {
                "accuracy": {
                    "macro": 0.795450210047151,
                    "micro": 0.7873716731567599
                },
                "classes": {
                    "stem": {
                        "prec": 0.7752213250316179,
                        "rec": 0.7660177841864936,
                        "f1": 0.7705920750429127
                    },
                    "gram": {
                        "prec": 0.8792302587923025,
                        "rec": 0.8717105263157895,
                        "f1": 0.8754542451271886
                    }
                },
                "bleu": 0.7818763406331335,
                "error_rate": 0.16393246715744542
            },
            "characters": {
                "error_rate": 0.1519105268295582
            }
        },
        "segmentation": {
            "accuracy": 0.6672593909757724,
            "precision": 0.904181645749173,
            "recall": 0.9050059644186259,
            "f1": 0.9035791100836053,
            "edit_distance": 0.7470549010891309
        },
        "alignment": 0.9996063654221635
    },
    "dido1241": {
        "glossing": {
            "words": {
                "accuracy": {
                    "macro": 0.8553005137057696,
                    "micro": 0.8487305312566674
                },
                "bleu": 0.6901993946140881,
                "error_rate": 0.1369660630928397
            },
            "morphemes": {
                "accuracy": {
                    "macro": 0.8325699916227847,
                    "micro": 0.8091421143847487
                },
                "classes": {
                    "stem": {
                        "prec": 0.8042414355628059,
                        "rec": 0.797365988909427,
                        "f1": 0.8007889546351086
                    },
                    "gram": {
                        "prec": 0.8527957816104581,
                        "rec": 0.8485080336648814,
                        "f1": 0.8506465044926583
                    }
                },
                "bleu": 0.873951680579539,
                "error_rate": 0.08099675272091056
            },
            "characters": {
                "error_rate": 0.06529082687633188
            }
        },
        "segmentation": {
            "accuracy": 0.6018099547511312,
            "precision": 0.9594452665512059,
            "recall": 0.9568116518842926,
            "f1": 0.9579662398518259,
            "edit_distance": 0.8235294117647058
        },
        "alignment": 1.0
    },
    "gitx1241": {
        "glossing": {
            "words": {
                "accuracy": {
                    "macro": 0.32318097244567834,
                    "micro": 0.3489583333333333
                },
                "bleu": 0.09255362979569297,
                "error_rate": 0.6768190275543217
            },
            "morphemes": {
                "accuracy": {
                    "macro": 0.19248963671078584,
                    "micro": 0.1736613603473227
                },
                "classes": {
                    "stem": {
                        "prec": 0.12195121951219512,
                        "rec": 0.11235955056179775,
                        "f1": 0.11695906432748537
                    },
                    "gram": {
                        "prec": 0.37212643678160917,
                        "rec": 0.3359273670557717,
                        "f1": 0.3531015678254942
                    }
                },
                "bleu": 0.32436786149587704,
                "error_rate": 0.5858584557846237
            },
            "characters": {
                "error_rate": 0.49138308075710013
            }
        },
        "segmentation": {
            "accuracy": 0.02702702702702703,
            "precision": 0.5931872677460912,
            "recall": 0.5169008764366342,
            "f1": 0.548126414536926,
            "edit_distance": 8.945945945945946
        },
        "alignment": 0.9977789109864582
    },
    "lezg1247": {
        "glossing": {
            "words": {
                "accuracy": {
                    "macro": 0.5522339406152714,
                    "micro": 0.5412621359223301
                },
                "bleu": 0.20517939259562404,
                "error_rate": 0.4477660593847287
            },
            "morphemes": {
                "accuracy": {
                    "macro": 0.5113001617976712,
                    "micro": 0.4463276836158192
                },
                "classes": {
                    "stem": {
                        "prec": 0.43640897755610975,
                        "rec": 0.4268292682926829,
                        "f1": 0.4315659679408138
                    },
                    "gram": {
                        "prec": 0.5709876543209876,
                        "rec": 0.563165905631659,
                        "f1": 0.5670498084291188
                    }
                },
                "bleu": 0.5318871476001765,
                "error_rate": 0.3567552921223536
            },
            "characters": {
                "error_rate": 0.3008264412201984
            }
        },
        "segmentation": {
            "accuracy": 0.1320754716981132,
            "precision": 0.78309926554392,
            "recall": 0.79223246313126,
            "f1": 0.7861409566566503,
            "edit_distance": 5.3584905660377355
        },
        "alignment": 1.0
    },
    "natu1246": {
        "glossing": {
            "words": {
                "accuracy": {
                    "macro": 0.7676935730789484,
                    "micro": 0.7815217391304348
                },
                "bleu": 0.5670047612032905,
                "error_rate": 0.23398992860455298
            },
            "morphemes": {
                "accuracy": {
                    "macro": 0.6613099967114855,
                    "micro": 0.6531722054380664
                },
                "classes": {
                    "stem": {
                        "prec": 0.6220689655172413,
                        "rec": 0.5981432360742706,
                        "f1": 0.6098715348208248
                    },
                    "gram": {
                        "prec": 0.7242582897033158,
                        "rec": 0.7229965156794426,
                        "f1": 0.7236268526591109
                    }
                },
                "bleu": 0.7898420180642031,
                "error_rate": 0.17178344991491057
            },
            "characters": {
                "error_rate": 0.15359291959971352
            }
        },
        "segmentation": {
            "accuracy": 0.42424242424242425,
            "precision": 0.9236538313957521,
            "recall": 0.9195651399961148,
            "f1": 0.9206139763545755,
            "edit_distance": 1.505050505050505
        },
        "alignment": 1.0
    },
    "nyan1302": {
        "glossing": {
            "words": {
                "accuracy": {
                    "macro": 0.6370383089133089,
                    "micro": 0.6646646646646647
                },
                "bleu": 0.4023793140504586,
                "error_rate": 0.3629616910866911
            },
            "morphemes": {
                "accuracy": {
                    "macro": 0.717655373958742,
                    "micro": 0.7277882797731569
                },
                "classes": {
                    "stem": {
                        "prec": 0.7,
                        "rec": 0.680327868852459,
                        "f1": 0.6900237529691211
                    },
                    "gram": {
                        "prec": 0.8579052701801201,
                        "rec": 0.866576819407008,
                        "f1": 0.8622192423734495
                    }
                },
                "bleu": 0.6465510991789684,
                "error_rate": 0.27832764168153185
            },
            "characters": {
                "error_rate": 0.2622176727670473
            }
        },
        "segmentation": {
            "accuracy": 0.8064516129032258,
            "precision": 0.9347352244529662,
            "recall": 0.9428146674114416,
            "f1": 0.937918075562057,
            "edit_distance": 0.2620967741935484
        },
        "alignment": 1.0
    },
    "ruul1235": {
        "glossing": {
            "words": {
                "accuracy": {
                    "macro": 0.477807569474236,
                    "micro": 0.4971145919208574
                },
                "bleu": 0.2340124044257816,
                "error_rate": 0.49582677916011264
            },
            "morphemes": {
                "accuracy": {
                    "macro": 0.549108393832336,
                    "micro": 0.5456968773800457
                },
                "classes": {
                    "stem": {
                        "prec": 0.5245762711864407,
                        "rec": 0.4772552043176561,
                        "f1": 0.49979814291481633
                    },
                    "gram": {
                        "prec": 0.6513844757149342,
                        "rec": 0.6496152105024898,
                        "f1": 0.6504986400725294
                    }
                },
                "bleu": 0.6046175118545256,
                "error_rate": 0.32549984888736205
            },
            "characters": {
                "error_rate": 0.25298845952093146
            }
        },
        "segmentation": {
            "accuracy": 0.43243243243243246,
            "precision": 0.7655381367898754,
            "recall": 0.7714798482600338,
            "f1": 0.7657331993318125,
            "edit_distance": 3.7837837837837838
        },
        "alignment": 1.0
    },
    "uspa1245": {
        "glossing": {
            "words": {
                "accuracy": {
                    "macro": 0.8029255197099725,
                    "micro": 0.8181019332161688
                },
                "bleu": 0.6383829928500794,
                "error_rate": 0.19707448029002805
            },
            "morphemes": {
                "accuracy": {
                    "macro": 0.7962931478611699,
                    "micro": 0.7851829812555787
                },
                "classes": {
                    "stem": {
                        "prec": 0.7751322751322751,
                        "rec": 0.7595593000648088,
                        "f1": 0.7672667757774141
                    },
                    "gram": {
                        "prec": 0.8539646320593268,
                        "rec": 0.8486394557823129,
                        "f1": 0.8512937162354278
                    }
                },
                "bleu": 0.8140565922355709,
                "error_rate": 0.15578204432003018
            },
            "characters": {
                "error_rate": 0.113833847576308
            }
        },
        "segmentation": {
            "accuracy": 0.46996466431095407,
            "precision": 0.851365027095125,
            "recall": 0.8518072475227955,
            "f1": 0.8507255888662221,
            "edit_distance": 0.9734982332155477
        },
        "alignment": 1.0
    },
    "all": {
        "glossing": {
            "words": {
                "accuracy": {
                    "macro": 0.752898837483581,
                    "micro": 0.7838351723707998
                },
                "bleu": 0.6172036441638985,
                "error_rate": 0.24498922180511165
            },
            "morphemes": {
                "accuracy": {
                    "macro": 0.7781700770926635,
                    "micro": 0.7648031523765965
                },
                "classes": {
                    "stem": {
                        "prec": 0.7586423444976077,
                        "rec": 0.7457741717376606,
                        "f1": 0.7521532235349927
                    },
                    "gram": {
                        "prec": 0.8445781616907078,
                        "rec": 0.83846057780368,
                        "f1": 0.8415082515145186
                    }
                },
                "bleu": 0.7926061427585915,
                "error_rate": 0.169015999350529
            },
            "characters": {
                "error_rate": 0.15110576612425958
            }
        },
        "segmentation": {
            "accuracy": 0.636376874908985,
            "precision": 0.8994854560181685,
            "recall": 0.9001441963555502,
            "f1": 0.8987720817101085,
            "edit_distance": 0.9675258482597933
        },
        "alignment": 0.999730138013807
    }
}