{
    "ainu1240": {
        "glossing": {
            "words": {
                "accuracy": {
                    "macro": 0.8699910870673586,
                    "micro": 0.8721153846153846
                },
                "bleu": 0.7388803978258325,
                "error_rate": 0.1233133250929863
            },
            "morphemes": {
                "accuracy": {
                    "macro": 0.8214408186108936,
                    "micro": 0.7999323524437679
                },
                "classes": {
                    "stem": {
                        "prec": 0.7898864250946458,
                        "rec": 0.7772751463544438,
                        "f1": 0.783530042918455
                    },
                    "gram": {
                        "prec": 0.8620569233455562,
                        "rec": 0.86235807860262,
                        "f1": 0.8622074746769123
                    }
                },
                "bleu": 0.8636868479963987,
                "error_rate": 0.10205984628119211
            },
            "characters": {
                "error_rate": 0.10074707951482963
            }
        },
        "segmentation": {
            "accuracy": 0.7542372881355932,
            "precision": 0.9563728637396335,
            "recall": 0.9590401814617072,
            "f1": 0.9572085340975516,
            "edit_distance": 0.42033898305084744
        },
        "alignment": 0.9928576782718036
    },
    "arap1274": {
        "glossing": {
            "words": {
                "accuracy": {
                    "macro": 0.7483933936376553,
                    "micro": 0.7759379954201162
                },
                "bleu": 0.6073880812876734,
                "error_rate": 0.25171423261846976
            },
            "morphemes": {
                "accuracy": {
                    "macro": 0.7926492549554661,
                    "micro": 0.7858591059762495
                },
                "classes": {
                    "stem": {
                        "prec": 0.7740302720591814,
                        "rec": 0.7644316270127374,
                        "f1": 0.7692010059972915
                    },
                    "gram": {
                        "prec": 0.8804405520169851,
                        "rec": 0.8730263157894737,
                        "f1": 0.8767177589852009
                    }
                },
                "bleu": 0.7789310981768617,
                "error_rate": 0.16669164872804793
            },
            "characters": {
                "error_rate": 0.1518260774087935
            }
        },
        "segmentation": {
            "accuracy": 0.6574794398755279,
            "precision": 0.9017603857240243,
            "recall": 0.9018166458550798,
            "f1": 0.900751361647231,
            "edit_distance": 0.7406090242276061
        },
        "alignment": 0.9940406013610504
    },
    "dido1241": {
        "glossing": {
            "words": {
                "accuracy": {
                    "macro": 0.86659118449899,
                    "micro": 0.8598250480051205
                },
                "bleu": 0.6936693960500355,
                "error_rate": 0.13284180114038974
            },
            "morphemes": {
                "accuracy": {
                    "macro": 0.8387480751029457,
                    "micro": 0.8108752166377816
                },
                "classes": {
                    "stem": {
                        "prec": 0.8073351903435468,
                        "rec": 0.8036044362292052,
                        "f1": 0.8054654932839278
                    },
                    "gram": {
                        "prec": 0.8506529134203884,
                        "rec": 0.8473057164717456,
                        "f1": 0.8489760157704523
                    }
                },
                "bleu": 0.8762509360770797,
                "error_rate": 0.07874873733290136
            },
            "characters": {
                "error_rate": 0.06447553902037233
            }
        },
        "segmentation": {
            "accuracy": 0.6221719457013575,
            "precision": 0.9692187773772323,
            "recall": 0.9685686816904849,
            "f1": 0.9687684378881721,
            "edit_distance": 0.748868778280543
        },
        "alignment": 0.9976997578365635
    },
    "gitx1241": {
        "glossing": {
            "words": {
                "accuracy": {
                    "macro": 0.3206446662329016,
                    "micro": 0.3229166666666667
                },
                "bleu": 0.08583321078376799,
                "error_rate": 0.672077668401198
            },
            "morphemes": {
                "accuracy": {
                    "macro": 0.21505700865845462,
                    "micro": 0.1678726483357453
                },
                "classes": {
                    "stem": {
                        "prec": 0.0970464135021097,
                        "rec": 0.08614232209737828,
                        "f1": 0.09126984126984128
                    },
                    "gram": {
                        "prec": 0.37681159420289856,
                        "rec": 0.33722438391699094,
                        "f1": 0.35592060232717315
                    }
                },
                "bleu": 0.3084417000883111,
                "error_rate": 0.5804337241833732
            },
            "characters": {
                "error_rate": 0.4851432864830444
            }
        },
        "segmentation": {
            "accuracy": 0.0,
            "precision": 0.6199531454293201,
            "recall": 0.5562335648683874,
            "f1": 0.581724822025423,
            "edit_distance": 7.5675675675675675
        },
        "alignment": 0.9674330597834192
    },
    "lezg1247": {
        "glossing": {
            "words": {
                "accuracy": {
                    "macro": 0.5503069368014751,
                    "micro": 0.5194174757281553
                },
                "bleu": 0.20963275831001008,
                "error_rate": 0.4394504755974467
            },
            "morphemes": {
                "accuracy": {
                    "macro": 0.5426161833510263,
                    "micro": 0.4943502824858757
                },
                "classes": {
                    "stem": {
                        "prec": 0.47890818858560796,
                        "rec": 0.47073170731707314,
                        "f1": 0.4747847478474785
                    },
                    "gram": {
                        "prec": 0.6303680981595092,
                        "rec": 0.6255707762557078,
                        "f1": 0.6279602750190985
                    }
                },
                "bleu": 0.5261161740619358,
                "error_rate": 0.35018935258454703
            },
            "characters": {
                "error_rate": 0.2721812483028774
            }
        },
        "segmentation": {
            "accuracy": 0.18867924528301888,
            "precision": 0.833107764616242,
            "recall": 0.8384543899785928,
            "f1": 0.8347613238490212,
            "edit_distance": 4.811320754716981
        },
        "alignment": 0.9860703411028916
    },
    "natu1246": {
        "glossing": {
            "words": {
                "accuracy": {
                    "macro": 0.7676777920025615,
                    "micro": 0.7728260869565218
                },
                "bleu": 0.5614657146516938,
                "error_rate": 0.23232220799743847
            },
            "morphemes": {
                "accuracy": {
                    "macro": 0.6773359478084675,
                    "micro": 0.6604229607250756
                },
                "classes": {
                    "stem": {
                        "prec": 0.6174863387978142,
                        "rec": 0.5994694960212201,
                        "f1": 0.6083445491251682
                    },
                    "gram": {
                        "prec": 0.7391812865497076,
                        "rec": 0.7340301974448316,
                        "f1": 0.7365967365967365
                    }
                },
                "bleu": 0.7762634342934925,
                "error_rate": 0.17382889283811026
            },
            "characters": {
                "error_rate": 0.14422526946247624
            }
        },
        "segmentation": {
            "accuracy": 0.43434343434343436,
            "precision": 0.9324158445996252,
            "recall": 0.9242724976726665,
            "f1": 0.9276004636512315,
            "edit_distance": 1.3434343434343434
        },
        "alignment": 0.996494901872922
    },
    "nyan1302": {
        "glossing": {
            "words": {
                "accuracy": {
                    "macro": 0.6292698117294893,
                    "micro": 0.6566566566566566
                },
                "bleu": 0.375924574930307,
                "error_rate": 0.3707301882705108
            },
            "morphemes": {
                "accuracy": {
                    "macro": 0.699244897786169,
                    "micro": 0.7057340894770007
                },
                "classes": {
                    "stem": {
                        "prec": 0.6855036855036855,
                        "rec": 0.6533957845433255,
                        "f1": 0.6690647482014388
                    },
                    "gram": {
                        "prec": 0.8253131179960448,
                        "rec": 0.8436657681940701,
                        "f1": 0.8343885371542819
                    }
                },
                "bleu": 0.6312541003755101,
                "error_rate": 0.29232910840477266
            },
            "characters": {
                "error_rate": 0.26889550325290645
            }
        },
        "segmentation": {
            "accuracy": 0.7741935483870968,
            "precision": 0.9249706465788059,
            "recall": 0.9392146551924779,
            "f1": 0.931069563179618,
            "edit_distance": 0.31048387096774194
        },
        "alignment": 0.999615975422427
    },
    "ruul1235": {
        "glossing": {
            "words": {
                "accuracy": {
                    "macro": 0.4993850993850993,
                    "micro": 0.5094806265457543
                },
                "bleu": 0.2363546601253163,
                "error_rate": 0.4708708708708711
            },
            "morphemes": {
                "accuracy": {
                    "macro": 0.5627424969272236,
                    "micro": 0.5502665651180503
                },
                "classes": {
                    "stem": {
                        "prec": 0.5349439171699741,
                        "rec": 0.4780262143407864,
                        "f1": 0.5048859934853419
                    },
                    "gram": {
                        "prec": 0.6537943421643466,
                        "rec": 0.6591217745586239,
                        "f1": 0.6564472497745717
                    }
                },
                "bleu": 0.6178638716002991,
                "error_rate": 0.3109714277412937
            },
            "characters": {
                "error_rate": 0.2387436454368494
            }
        },
        "segmentation": {
            "accuracy": 0.4144144144144144,
            "precision": 0.7657059799216662,
            "recall": 0.768405683550162,
            "f1": 0.7642899271259446,
            "edit_distance": 2.7027027027027026
        },
        "alignment": 0.9750270928422645
    },
    "uspa1245": {
        "glossing": {
            "words": {
                "accuracy": {
                    "macro": 0.7920955516803577,
                    "micro": 0.8101933216168717
                },
                "bleu": 0.6325120161141187,
                "error_rate": 0.20790444831964278
            },
            "morphemes": {
                "accuracy": {
                    "macro": 0.8019992693800122,
                    "micro": 0.7941088961618565
                },
                "classes": {
                    "stem": {
                        "prec": 0.784953395472703,
                        "rec": 0.7640959170447181,
                        "f1": 0.774384236453202
                    },
                    "gram": {
                        "prec": 0.8598979013045944,
                        "rec": 0.8594104308390023,
                        "f1": 0.8596540969662603
                    }
                },
                "bleu": 0.8062093494062461,
                "error_rate": 0.16212345516674143
            },
            "characters": {
                "error_rate": 0.12268236558858812
            }
        },
        "segmentation": {
            "accuracy": 0.4752650176678445,
            "precision": 0.8527311080106759,
            "recall": 0.8565774184590443,
            "f1": 0.8538307942133773,
            "edit_distance": 0.9522968197879859
        },
        "alignment": 0.9993666965823165
    },
    "all": {
        "glossing": {
            "words": {
                "accuracy": {
                    "macro": 0.7501180105226007,
                    "micro": 0.7804999688298735
                },
                "bleu": 0.6145334522688028,
                "error_rate": 0.24778009646551025
            },
            "morphemes": {
                "accuracy": {
                    "macro": 0.7776343860038463,
                    "micro": 0.76395876578827
                },
                "classes": {
                    "stem": {
                        "prec": 0.7583233532934132,
                        "rec": 0.7445907808090311,
                        "f1": 0.7513943277560222
                    },
                    "gram": {
                        "prec": 0.8429767636592004,
                        "rec": 0.8381517327505463,
                        "f1": 0.8405573240098105
                    }
                },
                "bleu": 0.7904374059975058,
                "error_rate": 0.17038387980979758
            },
            "characters": {
                "error_rate": 0.15047104041356638
            }
        },
        "segmentation": {
            "accuracy": 0.6305519149555847,
            "precision": 0.8993877136886447,
            "recall": 0.900154798582782,
            "f1": 0.8987490464717787,
            "edit_distance": 0.8875782728993739
        },
        "alignment": 0.9937233244983509
    }
}